mcp_gazette_archiver/server.py
mcp_gazette_archiver/prompts/__init__.py
mcp_gazette_archiver/prompts/archive_queries.py
mcp_gazette_archiver/prompts/classification_prompts.py
mcp_gazette_archiver/resources/__init__.py
mcp_gazette_archiver/resources/archive_stats.py
mcp_gazette_archiver/resources/gazette_metadata.py
mcp_gazette_archiver/utils/__init__.py
mcp_gazette_archiver/utils/data_formatters.py
mcp_gazette_archiver-0.1.4.dist-info/METADATA
mcp_gazette_archiver-0.1.4.dist-info/WHEEL
mcp_gazette_archiver-0.1.4.dist-info/entry_points.txt
mcp_gazette_archiver-0.1.4.dist-info/top_level.txt
mcp_gazette_archiver-0.1.4.dist-info/RECORD
