Metadata-Version: 2.4
Name: mcp-gazette-archiver
Version: 0.1.4
Summary: FastMCP Server for Sri Lankan Gazette Archiver with auto-installed gztarchiver
Author-email: Isuru Rangana <isuru212@gmail.com>
Project-URL: Homepage, https://github.com/LDFLK/mcp-gazette-archiver
Project-URL: Repository, https://github.com/LDFLK/mcp-gazette-archiver
Requires-Python: >=3.8
Requires-Dist: fastmcp>=0.3.0
Requires-Dist: pydantic>=2.0.0
Requires-Dist: pyyaml>=6.0.0
Requires-Dist: typing-extensions>=4.0.0
Requires-Dist: pathlib
Requires-Dist: contextlib2
Requires-Dist: nest-asyncio>=1.5.0
Provides-Extra: dev
Requires-Dist: pytest>=6.0; extra == "dev"
Requires-Dist: black>=22.0.0; extra == "dev"
Requires-Dist: flake8>=4.0.0; extra == "dev"
Requires-Dist: mypy>=1.0.0; extra == "dev"
